cuda/euler_update_Interface.cpp
cuda/euler_update_Kernel.cu
cuda/fluxCal_1stOrder_Interface.cpp
cuda/fluxCal_1stOrder_Kernel.cu
cuda/fluxCal_2ndOrder_Interface.cpp
cuda/fluxCal_2ndOrder_Kernel.cu
cuda/fluxMask_Interface.cpp
cuda/fluxMask_Kernel.cu
cuda/frictionImplicit_andUpdate_Interface.cpp
cuda/frictionImplicit_andUpdate_Kernel.cu
cuda/gpu.cuh
cuda/infiltration_sewer_Interface.cpp
cuda/infiltration_sewer_Kernel.cu
cuda/setup.py
cuda/stationPrecipitation_Interface.cpp
cuda/stationPrecipitation_Kernel.cu
cuda/timeControl_Interface.cpp
cuda/timeControl_Kernel.cu
hipims/InputHipims.py
hipims/SWE.py
hipims/__init__.py
hipims/banner.txt
hipims/euler_update.so
hipims/flood.py
hipims/fluxCal_1stOrder.so
hipims/fluxCal_2ndOrder.so
hipims/fluxMask.so
hipims/frictionImplicit_andUpdate.so
hipims/get_sample.py
hipims/infiltration_sewer.so
hipims/postProcessing.py
hipims/preProcessing.py
hipims/stationPrecipitation.so
hipims/timeControl.so
hipims/toolkit.py
hipims/visualization.py
hipims/sample/input/DEM.tif
hipims/sample/input/Landcover.tif
hipims/sample/input/Q_source.xlsx
hipims/sample/input/Schools.zip
hipims/sample/input/depth.tif
hipims/sample/input/hux.tif
hipims/sample/input/huy.tif
hipims/sample/input/outline.cpg
hipims/sample/input/outline.dbf
hipims/sample/input/outline.prj
hipims/sample/input/outline.shp
hipims/sample/input/outline.shx
hipims/sample/input/rainMask.tif
hipims/sample/input/rainfall_source.txt
hipims-2.1.0.dist-info/LICENCE
hipims-2.1.0.dist-info/METADATA
hipims-2.1.0.dist-info/WHEEL
hipims-2.1.0.dist-info/top_level.txt
hipims-2.1.0.dist-info/RECORD
