Metadata-Version: 2.2
Name: hipims
Version: 2.1.0
Summary: HiPIMS names for High-Performance Integrated hydrodynamic Modelling System. It uses state-of-art numerical schemes (Godunov-type finite volume) to solve the 2D shallow water equations for flood simulations. To support high-resolution flood simulations, HiPIMS is implemented on multiple GPUs (Graphics Processing Unit) using CUDA/C++ languages to achieve high-performance computing.
Author-email: Jiaheng Zhao <jiaheng.zhao@fmglobal.com>, Xue Tong <x.tong2@lboro.ac.uk>
Maintainer-email: Xue Tong <x.tong2@lboro.ac.uk>
Project-URL: Homepage, https://example.com
Project-URL: Documentation, https://readthedocs.org
Project-URL: Repository, https://github.com/me/spam.git
Project-URL: Bug Tracker, https://github.com/me/spam/issues
Project-URL: Changelog, https://github.com/me/spam/blob/master/CHANGELOG.md
Keywords: flood,flooding,flood-modelling
Classifier: Development Status :: 4 - Beta
Classifier: Programming Language :: Python
Classifier: Programming Language :: C++
Requires-Python: >=3.9
License-File: LICENCE
Requires-Dist: matplotlib
Requires-Dist: seaborn
Requires-Dist: rasterio
Requires-Dist: geopandas
Requires-Dist: spicy
Requires-Dist: openpyxl
